hypercurrent_metering/__init__.py
hypercurrent_metering/api_client.py
hypercurrent_metering/configuration.py
hypercurrent_metering/rest.py
hypercurrent_metering/api/__init__.py
hypercurrent_metering/api/api_events_controller_api.py
hypercurrent_metering/api/metering_controller_api.py
hypercurrent_metering/hypercurrent_metering_client/__init__.py
hypercurrent_metering/hypercurrent_metering_client/api_event_dto.py
hypercurrent_metering/hypercurrent_metering_client/metering_request_dto.py
test/__init__.py
test/test_api_event_dto.py
test/test_api_events_controller_api.py
test/test_metering_controller_api.py
test/test_metering_request_dto.py
hypercurrent_metering-1.0.0.dist-info/METADATA
hypercurrent_metering-1.0.0.dist-info/WHEEL
hypercurrent_metering-1.0.0.dist-info/top_level.txt
hypercurrent_metering-1.0.0.dist-info/RECORD
